idslib/__init__.py
idslib/data/__init__.py
idslib-1.0.0.1606697775.dist-info/LICENSE
idslib-1.0.0.1606697775.dist-info/METADATA
idslib-1.0.0.1606697775.dist-info/WHEEL
idslib-1.0.0.1606697775.dist-info/top_level.txt
idslib-1.0.0.1606697775.dist-info/RECORD
