Metadata-Version: 2.1
Name: idslib
Version: 1.0.0.1606697775
Summary: IDS Python lib to interact with piveau-hub API
Home-page: https://github.com/MGDS-development/idslib
Author: Daniel Doña
Author-email: ddona@delicias.dia.fi.upm.es
License: Apache 2.0
Platform: UNKNOWN
Classifier: Programming Language :: Python :: 3
Classifier: License :: OSI Approved :: Apache Software License
Classifier: Operating System :: OS Independent
Requires-Python: >=3.6
Requires-Dist: rdflib
